sirp/__init__.py
sirp/client.py
sirp/parameters.py
sirp/sirp.py
python_sirp-1.0.2.dist-info/LICENSE
python_sirp-1.0.2.dist-info/METADATA
python_sirp-1.0.2.dist-info/WHEEL
python_sirp-1.0.2.dist-info/top_level.txt
python_sirp-1.0.2.dist-info/RECORD
