Metadata-Version: 2.1
Name: python-sirp
Version: 1.0.2
Author-email: Grigory Efimov <grigory.efimov@gmail.com>
Maintainer-email: Grigory Efimov <grigory.efimov@gmail.com>
License: MIT License
Project-URL: Homepage, https://github.com/fb929/python-sirp
Project-URL: Documentation, https://github.com/fb929/python-sirp
Project-URL: Repository, https://github.com/fb929/python-sirp
License-File: LICENSE
Requires-Dist: pycryptodome >=3.21.0
